{"cameraMode":{"drawMode":0,"name":"Shaded","section":"Shading Mode"},"sceneLighting":true,"audioPlay":false,"sceneViewState":{"showFog":true,"showMaterialUpdate":true,"showSkybox":true,"showFlares":true,"showImageEffects":true,"showParticleSystems":true,"showVisualEffectGraphs":true,"m_FxEnabled":true},"in2DMode":false,"pivot":{"x":176.1508331298828,"y":95.05558776855469,"z":-22.81977653503418},"rotation":{"x":0.19750070571899415,"y":-0.7063119411468506,"z":0.21602469682693482,"w":0.644797146320343},"size":27.473533630371095,"orthographic":false}